{
  "character": "ronin",
  "animation": "cross",
  "sourceDir": "C:\\dev\\FIghtcore-codex-work\\sprite-combat-game\\public\\sprites\\frames-pack\\ronin\\cross",
  "outputDir": "C:\\dev\\FIghtcore-codex-work\\sprite-combat-game\\public\\sprites\\frames-cleaned\\ronin\\cross",
  "qaDir": "C:\\dev\\FIghtcore-codex-work\\sprite-combat-game\\public\\sprites\\qa-cleaned\\ronin\\cross",
  "frameCount": 5,
  "totals": {
    "transparentRgbCleared": 29243,
    "pixelsMadeTransparent": 0,
    "pixelsDecontaminated": 0,
    "pixelsRecoloredFromNeighbor": 0,
    "suspectedWhiteHaloPixelsRemaining": 0,
    "edgePixelsTouchingCanvasBoundary": 0
  },
  "warnings": [],
  "frames": [
    {
      "frame": "0001.png",
      "sourcePath": "C:\\dev\\FIghtcore-codex-work\\sprite-combat-game\\public\\sprites\\frames-pack\\ronin\\cross\\0001.png",
      "outputPath": "C:\\dev\\FIghtcore-codex-work\\sprite-combat-game\\public\\sprites\\frames-cleaned\\ronin\\cross\\0001.png",
      "beforeSuspectedWhiteHaloPixels": 0,
      "suspectedWhiteHaloPixelsRemaining": 0,
      "transparentRgbCleared": 4883,
      "madeTransparent": 0,
      "decontaminated": 0,
      "neighborRecolored": 0,
      "edgePixelsTouchingCanvasBoundary": 0,
      "warnings": []
    },
    {
      "frame": "0002.png",
      "sourcePath": "C:\\dev\\FIghtcore-codex-work\\sprite-combat-game\\public\\sprites\\frames-pack\\ronin\\cross\\0002.png",
      "outputPath": "C:\\dev\\FIghtcore-codex-work\\sprite-combat-game\\public\\sprites\\frames-cleaned\\ronin\\cross\\0002.png",
      "beforeSuspectedWhiteHaloPixels": 0,
      "suspectedWhiteHaloPixelsRemaining": 0,
      "transparentRgbCleared": 5277,
      "madeTransparent": 0,
      "decontaminated": 0,
      "neighborRecolored": 0,
      "edgePixelsTouchingCanvasBoundary": 0,
      "warnings": []
    },
    {
      "frame": "0003.png",
      "sourcePath": "C:\\dev\\FIghtcore-codex-work\\sprite-combat-game\\public\\sprites\\frames-pack\\ronin\\cross\\0003.png",
      "outputPath": "C:\\dev\\FIghtcore-codex-work\\sprite-combat-game\\public\\sprites\\frames-cleaned\\ronin\\cross\\0003.png",
      "beforeSuspectedWhiteHaloPixels": 0,
      "suspectedWhiteHaloPixelsRemaining": 0,
      "transparentRgbCleared": 6074,
      "madeTransparent": 0,
      "decontaminated": 0,
      "neighborRecolored": 0,
      "edgePixelsTouchingCanvasBoundary": 0,
      "warnings": []
    },
    {
      "frame": "0004.png",
      "sourcePath": "C:\\dev\\FIghtcore-codex-work\\sprite-combat-game\\public\\sprites\\frames-pack\\ronin\\cross\\0004.png",
      "outputPath": "C:\\dev\\FIghtcore-codex-work\\sprite-combat-game\\public\\sprites\\frames-cleaned\\ronin\\cross\\0004.png",
      "beforeSuspectedWhiteHaloPixels": 0,
      "suspectedWhiteHaloPixelsRemaining": 0,
      "transparentRgbCleared": 8440,
      "madeTransparent": 0,
      "decontaminated": 0,
      "neighborRecolored": 0,
      "edgePixelsTouchingCanvasBoundary": 0,
      "warnings": []
    },
    {
      "frame": "0005.png",
      "sourcePath": "C:\\dev\\FIghtcore-codex-work\\sprite-combat-game\\public\\sprites\\frames-pack\\ronin\\cross\\0005.png",
      "outputPath": "C:\\dev\\FIghtcore-codex-work\\sprite-combat-game\\public\\sprites\\frames-cleaned\\ronin\\cross\\0005.png",
      "beforeSuspectedWhiteHaloPixels": 0,
      "suspectedWhiteHaloPixelsRemaining": 0,
      "transparentRgbCleared": 4569,
      "madeTransparent": 0,
      "decontaminated": 0,
      "neighborRecolored": 0,
      "edgePixelsTouchingCanvasBoundary": 0,
      "warnings": []
    }
  ]
}