{
  "entityId": "ronin",
  "animationId": "dash",
  "note": "Measured from runtime-preferred PNG path when present, with metadata/canvas included for comparison.",
  "idleReference": {
    "bodyHeight": 118,
    "bodyWidth": 64,
    "baselineY": 148,
    "source": "idle metadata/runtime PNG median"
  },
  "outputCanvas": {
    "w": 224,
    "h": 160
  },
  "normalizedScale": 0.28028503562945367,
  "targetBodyHeight": 118,
  "frames": [
    {
      "frame": "0001",
      "runtimeFramePath": "C:\\dev\\FIghtcore-codex-work\\sprite-combat-game\\public\\sprites\\frames-cleaned\\ronin\\dash\\0001.png",
      "manualOverridePath": "C:\\dev\\FIghtcore-codex-work\\sprite-combat-game\\public\\sprites\\manual-overrides\\ronin\\dash\\0001.png",
      "sourcePriority": "frames-cleaned",
      "outputCanvas": {
        "w": 224,
        "h": 160
      },
      "runtimeDrawScale": 0.8429,
      "finalRenderedBodyHeight": 118.01,
      "visibleBodyHeight": 140,
      "visibleBodyWidth": 81,
      "heightVsIdle": 1.1864,
      "widthVsIdle": 1.2656,
      "topY": 8,
      "bottomFeetY": 147,
      "baselineY": 148,
      "baselineShift": 0,
      "centerX": 112.5,
      "centerY": 78,
      "torsoCoreHeightEstimate": 47.6,
      "torsoCoreWidthEstimate": 51.84,
      "lowerBodyLegZoneHeightEstimate": 58.8,
      "armReachExtensionBounds": {
        "x": 72,
        "y": 33.2,
        "w": 81,
        "h": 53.2
      },
      "warnings": [
        "body height 119% of idle"
      ],
      "likelyCauses": [
        "source art issue"
      ],
      "recommendedAction": [
        "manual override or source replacement preferred over deformation scaling"
      ]
    },
    {
      "frame": "0002",
      "runtimeFramePath": "C:\\dev\\FIghtcore-codex-work\\sprite-combat-game\\public\\sprites\\frames-cleaned\\ronin\\dash\\0002.png",
      "manualOverridePath": "C:\\dev\\FIghtcore-codex-work\\sprite-combat-game\\public\\sprites\\manual-overrides\\ronin\\dash\\0002.png",
      "sourcePriority": "frames-cleaned",
      "outputCanvas": {
        "w": 224,
        "h": 160
      },
      "runtimeDrawScale": 1,
      "finalRenderedBodyHeight": 118,
      "visibleBodyHeight": 118,
      "visibleBodyWidth": 93,
      "heightVsIdle": 1,
      "widthVsIdle": 1.4531,
      "topY": 30,
      "bottomFeetY": 147,
      "baselineY": 148,
      "baselineShift": 0,
      "centerX": 112.5,
      "centerY": 89,
      "torsoCoreHeightEstimate": 40.12,
      "torsoCoreWidthEstimate": 59.52,
      "lowerBodyLegZoneHeightEstimate": 49.56,
      "armReachExtensionBounds": {
        "x": 66,
        "y": 51.24,
        "w": 93,
        "h": 44.84
      },
      "warnings": [],
      "likelyCauses": [
        "within measured tolerance"
      ],
      "recommendedAction": []
    },
    {
      "frame": "0003",
      "runtimeFramePath": "C:\\dev\\FIghtcore-codex-work\\sprite-combat-game\\public\\sprites\\frames-cleaned\\ronin\\dash\\0003.png",
      "manualOverridePath": "C:\\dev\\FIghtcore-codex-work\\sprite-combat-game\\public\\sprites\\manual-overrides\\ronin\\dash\\0003.png",
      "sourcePriority": "frames-cleaned",
      "outputCanvas": {
        "w": 224,
        "h": 160
      },
      "runtimeDrawScale": 1.0351,
      "finalRenderedBodyHeight": 118,
      "visibleBodyHeight": 114,
      "visibleBodyWidth": 128,
      "heightVsIdle": 0.9661,
      "widthVsIdle": 2,
      "topY": 34,
      "bottomFeetY": 147,
      "baselineY": 148,
      "baselineShift": 0,
      "centerX": 112,
      "centerY": 91,
      "torsoCoreHeightEstimate": 38.76,
      "torsoCoreWidthEstimate": 81.92,
      "lowerBodyLegZoneHeightEstimate": 47.88,
      "armReachExtensionBounds": {
        "x": 48,
        "y": 54.52,
        "w": 128,
        "h": 43.32
      },
      "warnings": [],
      "likelyCauses": [
        "within measured tolerance"
      ],
      "recommendedAction": []
    },
    {
      "frame": "0004",
      "runtimeFramePath": "C:\\dev\\FIghtcore-codex-work\\sprite-combat-game\\public\\sprites\\frames-cleaned\\ronin\\dash\\0004.png",
      "manualOverridePath": "C:\\dev\\FIghtcore-codex-work\\sprite-combat-game\\public\\sprites\\manual-overrides\\ronin\\dash\\0004.png",
      "sourcePriority": "frames-cleaned",
      "outputCanvas": {
        "w": 224,
        "h": 160
      },
      "runtimeDrawScale": 1.1028,
      "finalRenderedBodyHeight": 118,
      "visibleBodyHeight": 107,
      "visibleBodyWidth": 136,
      "heightVsIdle": 0.9068,
      "widthVsIdle": 2.125,
      "topY": 41,
      "bottomFeetY": 147,
      "baselineY": 148,
      "baselineShift": 0,
      "centerX": 112,
      "centerY": 94.5,
      "torsoCoreHeightEstimate": 36.38,
      "torsoCoreWidthEstimate": 87.04,
      "lowerBodyLegZoneHeightEstimate": 44.94,
      "armReachExtensionBounds": {
        "x": 44,
        "y": 60.26,
        "w": 136,
        "h": 40.66
      },
      "warnings": [],
      "likelyCauses": [
        "within measured tolerance"
      ],
      "recommendedAction": []
    },
    {
      "frame": "0005",
      "runtimeFramePath": "C:\\dev\\FIghtcore-codex-work\\sprite-combat-game\\public\\sprites\\frames-cleaned\\ronin\\dash\\0005.png",
      "manualOverridePath": "C:\\dev\\FIghtcore-codex-work\\sprite-combat-game\\public\\sprites\\manual-overrides\\ronin\\dash\\0005.png",
      "sourcePriority": "frames-cleaned",
      "outputCanvas": {
        "w": 224,
        "h": 160
      },
      "runtimeDrawScale": 0.8429,
      "finalRenderedBodyHeight": 118.01,
      "visibleBodyHeight": 140,
      "visibleBodyWidth": 82,
      "heightVsIdle": 1.1864,
      "widthVsIdle": 1.2813,
      "topY": 8,
      "bottomFeetY": 147,
      "baselineY": 148,
      "baselineShift": 0,
      "centerX": 112,
      "centerY": 78,
      "torsoCoreHeightEstimate": 47.6,
      "torsoCoreWidthEstimate": 52.48,
      "lowerBodyLegZoneHeightEstimate": 58.8,
      "armReachExtensionBounds": {
        "x": 71,
        "y": 33.2,
        "w": 82,
        "h": 53.2
      },
      "warnings": [
        "body height 119% of idle"
      ],
      "likelyCauses": [
        "source art issue"
      ],
      "recommendedAction": [
        "manual override or source replacement preferred over deformation scaling"
      ]
    }
  ]
}
